quickinsights/__init__.py
quickinsights/_imports.py
quickinsights/advanced_config.py
quickinsights/ai_insights.py
quickinsights/architecture_patterns.py
quickinsights/async_core.py
quickinsights/big_data.py
quickinsights/caching.py
quickinsights/cloud_integration.py
quickinsights/config.py
quickinsights/core.py
quickinsights/dashboard.py
quickinsights/dask_integration.py
quickinsights/data_validation.py
quickinsights/distributed_computing.py
quickinsights/error_handling.py
quickinsights/explainable_ai.py
quickinsights/feature_engineering.py
quickinsights/feature_selection.py
quickinsights/io.py
quickinsights/memory_manager.py
quickinsights/memory_manager_v2.py
quickinsights/ml_pipeline.py
quickinsights/model_selection.py
quickinsights/modern_features.py
quickinsights/numpy_integration.py
quickinsights/pandas_integration.py
quickinsights/performance_optimizer_v2.py
quickinsights/plugin_system.py
quickinsights/profiling.py
quickinsights/realtime_ai.py
quickinsights/realtime_pipeline.py
quickinsights/security_utils.py
quickinsights/smart_cache.py
quickinsights/smart_cleaner.py
quickinsights/streaming.py
quickinsights/utils.py
quickinsights/visualizer.py
quickinsights/web_api.py
quickinsights/analysis/__init__.py
quickinsights/analysis/advanced_analysis.py
quickinsights/analysis/basic_analysis.py
quickinsights/automl/__init__.py
quickinsights/automl/continuous_learning.py
quickinsights/automl/explainability.py
quickinsights/automl/hyperparameter_tuning.py
quickinsights/automl/meta_learning.py
quickinsights/automl/model_selection.py
quickinsights/plugins/__init__.py
quickinsights/plugins/advanced_analyzer.py
quickinsights/plugins/custom_visualizer.py
quickinsights/plugins/smart_cleaner.py
quickinsights/visualization/__init__.py
quickinsights/visualization/advanced_charts.py
quickinsights/visualization/charts.py
quickinsights/visualization/maps.py
quickinsights/visualization/specialized_charts.py
quickinsights-0.4.0.dist-info/licenses/LICENSE
quickinsights-0.4.0.dist-info/METADATA
quickinsights-0.4.0.dist-info/WHEEL
quickinsights-0.4.0.dist-info/top_level.txt
quickinsights-0.4.0.dist-info/RECORD
