Metadata-Version: 2.4
Name: quickinsights
Version: 0.4.0
Summary: Enterprise-grade data analysis and insights library with plugin architecture, async operations, and advanced configuration management
Author-email: QuickInsights Team <erena6466@gmail.com>
Maintainer-email: QuickInsights Team <erena6466@gmail.com>
License: MIT
Project-URL: Homepage, https://github.com/erena6466/quickinsights
Project-URL: Documentation, https://github.com/erena6466/quickinsights/blob/main/docs/API_REFERENCE.md
Project-URL: Repository, https://github.com/erena6466/quickinsights.git
Project-URL: Bug Tracker, https://github.com/erena6466/quickinsights/issues
Project-URL: Source Code, https://github.com/erena6466/quickinsights
Project-URL: Download, https://github.com/erena6466/quickinsights/releases
Project-URL: Changelog, https://github.com/erena6466/quickinsights/blob/main/RELEASE_NOTES_v0.4.0.md
Keywords: data-analysis,machine-learning,visualization,automl,async,plugins,enterprise,pandas,numpy,scikit-learn,big-data,streaming,profiling,pandas-extension,parquet
Classifier: Development Status :: 5 - Production/Stable
Classifier: Intended Audience :: Developers
Classifier: Intended Audience :: Science/Research
Classifier: Intended Audience :: Financial and Insurance Industry
Classifier: Intended Audience :: Healthcare Industry
Classifier: Intended Audience :: Manufacturing
Classifier: License :: OSI Approved :: MIT License
Classifier: Operating System :: OS Independent
Classifier: Programming Language :: Python :: 3
Classifier: Programming Language :: Python :: 3.9
Classifier: Programming Language :: Python :: 3.10
Classifier: Programming Language :: Python :: 3.11
Classifier: Programming Language :: Python :: 3.12
Classifier: Topic :: Scientific/Engineering :: Information Analysis
Classifier: Topic :: Scientific/Engineering :: Artificial Intelligence
Classifier: Topic :: Scientific/Engineering :: Mathematics
Classifier: Topic :: Software Development :: Libraries :: Python Modules
Classifier: Topic :: Software Development :: Libraries :: Application Frameworks
Classifier: Topic :: Database :: Database Engines/Servers
Classifier: Topic :: Office/Business :: Financial :: Investment
Classifier: Topic :: Office/Business :: Financial :: Spreadsheet
Classifier: Framework :: AsyncIO
Classifier: Environment :: Console
Classifier: Environment :: Web Environment
Requires-Python: >=3.9
License-File: LICENSE
Requires-Dist: pandas>=1.5.0
Requires-Dist: numpy>=1.21.0
Requires-Dist: matplotlib>=3.5.0
Requires-Dist: seaborn>=0.11.0
Requires-Dist: plotly>=5.0.0
Requires-Dist: scipy>=1.9.0
Requires-Dist: scikit-learn>=1.1.0
Requires-Dist: psutil>=5.9.0
Requires-Dist: pyyaml>=6.0
Requires-Dist: toml>=0.10.0
Provides-Extra: dev
Requires-Dist: black>=23.0.0; extra == "dev"
Requires-Dist: isort>=5.12.0; extra == "dev"
Requires-Dist: flake8>=6.0.0; extra == "dev"
Requires-Dist: mypy>=1.3.0; extra == "dev"
Requires-Dist: pylint>=3.0.0; extra == "dev"
Requires-Dist: pytest>=7.0.0; extra == "dev"
Requires-Dist: pytest-cov>=4.0.0; extra == "dev"
Requires-Dist: pre-commit>=3.0.0; extra == "dev"
Requires-Dist: openpyxl>=3.1.0; extra == "dev"
Provides-Extra: io
Requires-Dist: openpyxl>=3.1.0; extra == "io"
Provides-Extra: security
Requires-Dist: bandit>=1.7.0; extra == "security"
Requires-Dist: safety>=2.3.0; extra == "security"
Provides-Extra: performance
Requires-Dist: numba>=0.57.0; extra == "performance"
Requires-Dist: dask>=2023.0.0; extra == "performance"
Provides-Extra: gpu
Requires-Dist: torch>=1.9.0; extra == "gpu"
Requires-Dist: cupy>=10.0.0; extra == "gpu"
Provides-Extra: cloud
Requires-Dist: boto3>=1.26.0; extra == "cloud"
Requires-Dist: azure-storage-blob>=12.14.0; extra == "cloud"
Requires-Dist: google-cloud-storage>=2.7.0; extra == "cloud"
Provides-Extra: fast
Requires-Dist: numba>=0.57.0; extra == "fast"
Requires-Dist: dask>=2023.0.0; extra == "fast"
Requires-Dist: joblib>=1.2.0; extra == "fast"
Provides-Extra: ml
Requires-Dist: torch>=1.9.0; extra == "ml"
Requires-Dist: xgboost>=1.7.0; extra == "ml"
Requires-Dist: lightgbm>=3.3.0; extra == "ml"
Requires-Dist: catboost>=1.1.0; extra == "ml"
Provides-Extra: web
Requires-Dist: fastapi>=0.100.0; extra == "web"
Requires-Dist: uvicorn>=0.20.0; extra == "web"
Requires-Dist: flask>=2.0.0; extra == "web"
Requires-Dist: pydantic>=2.0.0; extra == "web"
Provides-Extra: all
Requires-Dist: quickinsights[cloud,dev,fast,gpu,ml,performance,security,web]; extra == "all"
Dynamic: license-file
